nifi_api/__init__.py
nifi_api/_nbdev.py
nifi_api/dataflow.py
nifi_api/environment.py
nifi_api/rest.py
nifi_api/source_to_refined.py
nifi_api/tools.py
nifi_rest/__init__.py
nifi_rest/_nbdev.py
nifi_rest/dataflow.py
nifi_rest/environment.py
nifi_rest/rest.py
nifi_rest/source_to_refined.py
nifi_rest/tools.py
nifi_rest-0.0.3.dist-info/LICENSE
nifi_rest-0.0.3.dist-info/METADATA
nifi_rest-0.0.3.dist-info/WHEEL
nifi_rest-0.0.3.dist-info/entry_points.txt
nifi_rest-0.0.3.dist-info/top_level.txt
nifi_rest-0.0.3.dist-info/RECORD
