Metadata-Version: 2.1
Name: nifi-rest
Version: 0.0.3
Summary: Scripts for the NIFI API
Home-page: https://github.com/kikejimenez/nifi_rest/tree/main/
Author: kikejimenez
Author-email: physieira@gmail.com
License: Apache Software License 2.0
Keywords: nifi cloudera requests python
Platform: UNKNOWN
Classifier: Development Status :: 3 - Alpha
Classifier: Intended Audience :: Developers
Classifier: Natural Language :: English
Classifier: Programming Language :: Python :: 3.6
Classifier: Programming Language :: Python :: 3.7
Classifier: Programming Language :: Python :: 3.8
Classifier: License :: OSI Approved :: Apache Software License
Requires-Python: >=3.6
Requires-Dist: requests (>=2.25.1)
